Metadata-Version: 2.1
Name: api-key-client
Version: 0.1.10
Summary: Use with api-key-server
Author: Chunkai Meng
Author-email: willcute@gmail.com
Classifier: Programming Language :: Python :: 3
Classifier: License :: OSI Approved :: MIT License
Classifier: Operating System :: OS Independent
Requires-Python: >=3.6
License-File: LICENSE
